pathos/__info__.py
pathos/__init__.py
pathos/__main__.py
pathos/_ppserver_config.py
pathos/abstract_launcher.py
pathos/connection.py
pathos/core.py
pathos/hosts.py
pathos/maps.py
pathos/mp_map.py
pathos/multiprocessing.py
pathos/parallel.py
pathos/pools.py
pathos/portpicker.py
pathos/pp.py
pathos/pp_map.py
pathos/profile.py
pathos/python.py
pathos/selector.py
pathos/serial.py
pathos/server.py
pathos/threading.py
pathos/util.py
pathos/helpers/__init__.py
pathos/helpers/mp_helper.py
pathos/helpers/pp_helper.py
pathos/secure/__init__.py
pathos/secure/connection.py
pathos/secure/copier.py
pathos/secure/tunnel.py
pathos/tests/__init__.py
pathos/tests/__main__.py
pathos/tests/test_decorate.py
pathos/tests/test_join.py
pathos/tests/test_map.py
pathos/tests/test_maps.py
pathos/tests/test_mp.py
pathos/tests/test_pp.py
pathos/tests/test_random.py
pathos/tests/test_star.py
pathos/tests/test_with.py
pathos/xmlrpc/__init__.py
pathos/xmlrpc/server.py
pathos-0.3.3.data/scripts/pathos_connect
pathos-0.3.3.data/scripts/portpicker
pathos-0.3.3.dist-info/LICENSE
pathos-0.3.3.dist-info/METADATA
pathos-0.3.3.dist-info/WHEEL
pathos-0.3.3.dist-info/top_level.txt
pathos-0.3.3.dist-info/RECORD
